Workbook

Sheet DCF Model
B1: DCF Model
AP2: CAPM: | AQ2: =D9+(AB8*(D10-D9)) -> 0.097126697 | AU2: Discounted CFs | AV2: Entry | AW2: 2025 | AX2: 2026e | AY2: 2027e | AZ2: 2028e | BA2: 2029e | BB2: 2030e | BD2: DCF Model | BE2: 2025 | BF2: 2026e | BG2: 2027e | BH2: 2028e | BI2: 2029e | BJ2: 2030e | BK2: Total
B3: Assumptions | AP3: So, Re: | AQ3: 0.097 | AU3: Date | AV3: 31.12.2025 | AW3: 31.12.2025 | AX3: 31.12.2026 | AY3: 31.12.2027 | AZ3: 31.12.2028 | BA3: 31.12.2029 | BB3: 31.12.2030 | BD3: Discounted FCF | BF3: =AX11/(1+AQ10) -> 372.76501 | BG3: =AY11/(1+AQ10)^2 -> 490.4865 | BH3: =AZ11/(1+AQ10)^3 -> 1115.4513 | BI3: =BA11/(1+AQ10)^4 -> 1694.7686 | BJ3: =BB11/(1+AQ10)^5 -> 2443.626 | BK3: =SUM(BF3:BJ3) -> 6117.0974
B4: Perpetural Growth Rate | D4: 0.02 | AA4: We can't take the average of levered betas because each company has different debt levels. | AP4: Interest: | AQ4: ='Income Statement'!AA33 -> 3.5 | AU4: Time Periods | AX4: 1 | AY4: 2 | AZ4: 3 | BA4: 4 | BB4: 5
B5: Transaction Date | D5: =DATE(YEAR(TODAY()),12,31) -> 46022 | M5: (using Hamada Eq) | AA5: Instead, we unlever their betas, average the unlevered betas, and then re-lever using our unlevered beta and our projected debt-to-equity ratio for 2025 | AP5: Debt: | AQ5: ='Balance Sheet'!Z35 -> 86.62291 | AU5: EBIT (income from operations) | AX5: 848.15829 | AY5: 1616.4195 | AZ5: 2872.6337 | BA5: 4754.6551 | BB5: 7315.5196 | BD5: Terminal Value | BE5: =BB11*(1+D4)/(AQ10-D4) -> 56584.507
B6: Fiscal Year End | D6: =DATE(YEAR(TODAY()),12,31) -> 46022 | F6: Competitors | G6: Levered B | H6: Gearing | M6: Unlevered Beta | P6: Here, we have levered debt. However, in cases where we have no debt, then it will be unlevered beta. | AA6: Re-levering the average Unlevered beta calculated using our company's capital structure of 2025, as the transation y given here is 2025. | AP6: Rd: | AQ6: =AQ4/AQ5 -> 0.040405015 | AR6: (i% is interest/debt) | AU6: Tax Rate | AX6: 0.3 | AY6: 0.30048825 | AZ6: 0.30027447 | BA6: 0.30016575 | BB6: 0.3001077
B7: Current Price | D7: 39 | F7: Competitor A | G7: 1.3 | H7: 0.4 | J7: Means that D is 40% and E is 60% | M7: =G7/(1+(1-'Income Statement'!$AA$43)*H7) -> 1.0156266 | P7: For only unlevered beta: 1) Unlever all beta 2) Find their average | AP7: Equity: | AQ7: ='Balance Sheet'!Z40 -> 495.79673 | AR7: =(AQ7/AQ9) -> 0.85127062 | BD7: Discounted TV | BE7: =BE5/(1+AQ10)^5 -> 37324.133
B8: Shares Outstanding | D8: 1165 | F8: Competitor B | G8: 1.6 | H8: 0.55 | J8: Means that D is 55% and E is 45% | M8: =G8/(1+(1-'Income Statement'!$AA$43)*H8) -> 1.155237 | P8: For with levered beta: 1) Use Hamada Equation 2) You'll find your replaced beta | AA8: Company Beta: | AB8: =M10*(1+(1-'Income Statement'!AA43)*'Balance Sheet'!Z49) -> 1.2021116 | AP8: Debt: | AQ8: =AQ5 -> 86.62291 | AR8: =(AQ8/AQ9) -> 0.14872938 | AU8: (+) D&A | AX8: 100.97123 | AY8: 171.95952 | AZ8: 276.21478 | BA8: 417.07501 | BB8: 589.96126
B9: Risk Free Rate | D9: 0.025 | F9: Competitor C | G9: 1.5 | H9: 0.5 | J9: Means tht D is 50% and E is 50% | M9: =G9/(1+(1-'Income Statement'!$AA$43)*H9) -> 1.1111132 | P9: Levered beta is the equity beta. | AP9: Total: | AQ9: =SUM(AQ7:AQ8) -> 582.41964 | AR9: =SUM(AR7:AR8) -> 1 | AU9: (-) Capex | AX9: 231.94245 | AY9: 405.91905 | AZ9: 583.42956 | BA9: 1014.15 | BB9: 1555.9225 | BD9: Enterprise Value: | BE9: =SUM(BK3,BE7) -> 43441.23
B10: Market Return | D10: 0.085 | J10: Average | M10: =AVERAGE(M7:M9) -> 1.0939922 | P10: D/E ratio is one form of gearing ratio. | AP10: WACC: | AQ10: =((AQ7/(AQ9)*AQ3)+((AQ8/AQ9)*AQ6)*(1-'Income Statement'!AA43)) -> 0.086779809 | AU10: (-) Change in WCN | AX10: 57.626088 | AY10: 317.43606 | AZ10: 271.06367 | BA10: 366.2366 | BB10: 449.50425 | BD10: (+) Cash | BE10: ='Balance Sheet'!Z10 -> 376.36644
AU11: (=) FCF | AX11: =AX5*(1-AX6)-AX7+AX8-AX9-AX10 -> 405.11349 | AY11: =AY5*(1-AY6)-AY7+AY8-AY9-AY10 -> 579.30887 | AZ11: =AZ5*(1-AZ6)-AZ7+AZ8-AZ9-AZ10 -> 1431.7767 | BA11: =BA5*(1-BA6)-BA7+BA8-BA9-BA10 -> 2364.1589 | BB11: =BB5*(1-BB6)-BB7+BB8-BB9-BB10 -> 3704.6104 | BD11: (-) Debt | BE11: ='Balance Sheet'!Z30+'Balance Sheet'!Z33 -> 70
BD12: (=) Equity Value | BE12: =BE9+BE10-BE11 -> 43747.597
BD13: Equity Value/Share | BE13: =BE12/D8 -> 37.551585
BD14: (share price is overvalued)
B16: Q) Find the value of the company.
B17: Ans:
B19: Step 1: Find the Tax rate of each y in IS using the formula:
B25: Step 2: Take the tax rate of 2025, since here the transaction date is 2025.
B27: Step 3: Find the Unlevered Beta using the Hamada Equation.
B36: Step 4: Find the average of the three Unlevered Beta.
B38: Step 5: Find the D/E ratio in BS for all years.
B40: Step 6: Re-lever the average Unlevered beta, found in Step 4, using the D/E ratio of our company in 2025.
B41: This is your company's levered Beta now.
B43: Step 7: CAPM Calculation for finding Re
C48: Step 8: Write the Re from CAPM, the interest from 2025, the debt from 2025, and the calculated Rd.
C50: Step 9: Calculate WACC
C56: Step 10: Create the Discounted CFs table.
C58: Step 11: Create a new sheet to calculate Capex and then WCN
C60: Step 12: Calculate the FCFs.
C66: Step 13: Calulate using DCF model.
C82: Step 14: Sum the FCFs and TV to get the EV
C84: Step 15: Calculate the Equity Value
C86: Step 16: Calculate the Equity value per shares outstanding

Sheet Capex & WCN
B9: Date | C9: 2025 | D9: 2026e | E9: 2027e | F9: 2028e | G9: 2029e | H9: 2030e
B10: Net Fixed Assets | C10: ='Balance Sheet'!Z18 -> 110.85263 | D10: 211.82385 | E10: 383.78337 | F10: 659.99816 | G10: 1077.0732 | H10: 1667.0344
B11: Gross Value | C11: ='Balance Sheet'!Z20 -> 112.19025 | D11: ='Balance Sheet'!AE20 -> 201.94245 | E11: ='Balance Sheet'!AF20 -> 343.91905 | F11: ='Balance Sheet'!AG20 -> 552.42956 | G11: ='Balance Sheet'!AH20 -> 834.15002 | H11: ='Balance Sheet'!AI20 -> 1179.9225
B12: Disposals | C12: ='Balance Sheet'!Z47 -> 5.6095125 | D12: ='Balance Sheet'!AE47 -> 30 | E12: ='Balance Sheet'!AF47 -> 62 | F12: ='Balance Sheet'!AG47 -> 31 | G12: ='Balance Sheet'!AH47 -> 180 | H12: ='Balance Sheet'!AI47 -> 376
B13: Depreciation | C13: 56.095125 | D13: 100.97123 | E13: 171.95952 | F13: 276.21478 | G13: 417.07501 | H13: 589.96126
B14: Capex | D14: =(D10-C10)+D13+D12 -> 231.94245 | E14: =(E10-D10)+E13+E12 -> 405.91905 | F14: =(F10-E10)+F13+F12 -> 583.42956 | G14: =(G10-F10)+G13+G12 -> 1014.15 | H14: =(H10-G10)+H13+H12 -> 1555.9225
B23: Date | C23: 2025 | D23: 2026e | E23: 2027e | F23: 2028e | G23: 2029e | H23: 2030e
B24: WCN | C24: =('Balance Sheet'!Z12+'Balance Sheet'!Z14)-'Balance Sheet'!Z28 -> 72.03261 | D24: =('Balance Sheet'!AE12+'Balance Sheet'!AE14)-'Balance Sheet'!AE28 -> 129.6587 | E24: =('Balance Sheet'!AF12+'Balance Sheet'!AF14)-'Balance Sheet'!AF28 -> 447.09476 | F24: =('Balance Sheet'!AG12+'Balance Sheet'!AG14)-'Balance Sheet'!AG28 -> 718.15843 | G24: =('Balance Sheet'!AH12+'Balance Sheet'!AH14)-'Balance Sheet'!AH28 -> 1084.395 | H24: =('Balance Sheet'!AI12+'Balance Sheet'!AI14)-'Balance Sheet'!AI28 -> 1533.8993
B25: Change in WCN | D25: =D24-C24 -> 57.626088 | E25: =E24-D24 -> 317.43606 | F25: =F24-E24 -> 271.06367 | G25: =G24-F24 -> 366.2366 | H25: =H24-G24 -> 449.50425

Sheet Revenue (More Detailed)
A1: Revenue Breakdown (feeds into the Income Statement on the next tab)
A2: $ Values are in $'000s
A3: Blue = hard coded (not calculated) | F3: =K$3-1 -> -4 | K3: =P$3-1 -> -3 | P3: =U$3-1 -> -2 | U3: =Z$3-1 -> -1 | Z3: 0 | AE3: =Z3+1 -> 1 | AF3: =AE3+1 -> 2 | AG3: =AF3+1 -> 3 | AH3: =AG3+1 -> 4 | AI3: =AH3+1 -> 5
A4: SOURCE OF ALL DATA: EARNINGS PRESS RELEASE FROM IR WEBSITE OR SEC.GOV FILINGS
B5: =#REF! -> #REF! | F5: =#REF! -> #REF! | G5: =#REF! -> #REF! | K5: =#REF! -> #REF! | L5: =#REF! -> #REF! | P5: =#REF! -> #REF! | Q5: =#REF! -> #REF! | U5: =#REF! -> #REF! | V5: =#REF! -> #REF! | Z5: FY | AA5: =#REF! -> #REF! | AE5: Fye | AF5: FYE | AG5: =#REF! -> #REF! | AH5: =#REF! -> #REF! | AI5: =#REF! -> #REF!
B6: ="1Q"&RIGHT(F6,2)&"A" -> 1Q21A | C6: ="2Q"&RIGHT(F6,2)&"A" -> 2Q21A | D6: ="3Q"&RIGHT(F6,2)&"A" -> 3Q21A | E6: ="4Q"&RIGHT(F6,2)&"A" -> 4Q21A | F6: =YEAR(TODAY())+F$3 -> 2021 | G6: ="1Q"&RIGHT(K6,2)&"A" -> 1Q22A | H6: ="2Q"&RIGHT(K6,2)&"A" -> 2Q22A | I6: ="3Q"&RIGHT(K6,2)&"A" -> 3Q22A | J6: ="4Q"&RIGHT(K6,2)&"A" -> 4Q22A | K6: =YEAR(TODAY())+K$3 -> 2022 | L6: ="1Q"&RIGHT(P6,2)&"A" -> 1Q23A | M6: ="2Q"&RIGHT(P6,2)&"A" -> 2Q23A | N6: ="3Q"&RIGHT(P6,2)&"A" -> 3Q23A | O6: ="4Q"&RIGHT(P6,2)&"A" -> 4Q23A | P6: =YEAR(TODAY())+P$3 -> 2023 | Q6: 1Q19A | R6: 2Q19A | S6: 3Q19A | T6: 4Q19A | U6: =YEAR(TODAY())+U$3 -> 2024 | V6: =IF(MONTH(TODAY())>3,"1Q"&RIGHT(Z6,2)&"A","1Q"&RIGHT(Z6,2)&"A") -> 1Q25A | W6: =IF(MONTH(TODAY())>6,"2Q"&RIGHT(Z6,2)&"A","2Q"&RIGHT(Z6,2)&"A") -> 2Q25A | X6: =IF(MONTH(TODAY())>9,"3Q"&RIGHT(Z6,2)&"A","3Q"&RIGHT(Z6,2)&"A") -> 3Q25A | Y6: ="4Q"&RIGHT(Z6,2)&"A" -> 4Q25A | Z6: =YEAR(TODAY())+Z$3 -> 2025 | AA6: ="1Q"&RIGHT(AE6,3) -> 1Q26e | AB6: ="2Q"&RIGHT(AE6,3) -> 2Q26e | AC6: ="3Q"&RIGHT(AE6,3) -> 3Q26e | AD6: ="4Q"&RIGHT(AE6,3) -> 4Q26e | AE6: =YEAR(TODAY())+AE$3&"e" -> 2026e | AF6: =YEAR(TODAY())+AF$3&"e" -> 2027e | AG6: =YEAR(TODAY())+AG$3&"e" -> 2028e | AH6: =YEAR(TODAY())+AH$3&"e" -> 2029e | AI6: =YEAR(TODAY())+AI$3&"e" -> 2030e
A7: Sector Breakdown of Revenue
A9: Total Revenue | B9: =B13+B18 -> 4.5 | C9: =C13+C18 -> 7 | D9: =D13+D18 -> 21.5 | E9: =E13+E18 -> 32 | F9: =F13+F18 -> 65 | G9: =G13+G18 -> 9.8 | H9: =H13+H18 -> 15.2 | I9: =I13+I18 -> 47 | ... AI9: =AI13+AI18 -> 11799.225
A10: YOY change | G10: =G9/B9-1 -> 1.1777778 | H10: =H9/C9-1 -> 1.1714286 | I10: =I9/D9-1 -> 1.1860465 | J10: =J9/E9-1 -> 1.1875 | K10: =K9/F9-1 -> 1.1846154 | L10: =L9/G9-1 -> 1.0846939 | M10: =M9/H9-1 -> 1.0802632 | N10: =N9/I9-1 -> 1.0904255 | ... AE10: =AE9/Z9-1 -> 0.8 | AF10: =AF9/AE9-1 -> 0.70305474 | AG10: =AG9/AF9-1 -> 0.6062779 | AH10: =AH9/AG9-1 -> 0.5099663 | AI10: =AI9/AH9-1 -> 0.41452075
A11: QOQ change | C11: =C9/B9-1 -> 0.55555556 | D11: =D9/C9-1 -> 2.0714286 | E11: =E9/D9-1 -> 0.48837209 | G11: =G9/E9-1 -> -0.69375 | H11: =H9/G9-1 -> 0.55102041 | I11: =I9/H9-1 -> 2.0921053 | J11: =J9/I9-1 -> 0.4893617 | L11: =L9/J9-1 -> -0.70814286 | M11: =M9/L9-1 -> 0.54772394 | N11: =N9/M9-1 -> 2.1072106 | O11: =O9/N9-1 -> 0.49007634 | Q11: =Q9/O9-1 -> -0.72223361 | R11: =R9/Q9-1 -> 0.54555515 | S11: =S9/R9-1 -> 2.1171838 | T11: =T9/S9-1 -> 0.49054437 | V11: =V9/T9-1 -> -0.73605147 | W11: =W9/V9-1 -> 0.54446293 | X11: =X9/W9-1 -> 2.1222169 | Y11: =Y9/X9-1 -> 0.49077943 | AA11: =AA9/Y9-1 -> -0.74960909 | AB11: =AB9/AA9-1 -> 0.54446293 | AC11: =AC9/AB9-1 -> 2.1222169 | AD11: =AD9/AC9-1 -> 0.49077943
A13: REVENUE Product #1 | B13: 4 | C13: 6 | D13: 20 | E13: 30 | F13: =SUM(B13:E13) -> 60 | G13: 8.8 | H13: 13.2 | I13: 44 | J13: 66 | K13: =SUM(G13:J13) -> 132 | L13: 18.48 | M13: 27.72 | N13: 92.4 | O13: 138.6 | P13: =SUM(L13:O13) -> 277.2 | Q13: 36.96 | R13: 55.44 | S13: =N13*2 -> 184.8 | T13: 277.2 | U13: =SUM(Q13:T13) -> 554.4 | V13: 70.224 | W13: 105.336 | X13: =S13*1.9 -> 351.12 | Y13: 526.68 | Z13: =SUM(V13:Y13) -> 1053.36 | AA13: =V13*(1+AA14) -> 126.4032 | AB13: =W13*(1+AB14) -> 189.6048 | AC13: =X13*(1+AC14) -> 632.016 | AD13: =Y13*(1+AD14) -> 948.024 | AE13: =SUM(AA13:AD13) -> 1896.048 | AF13: =IF(AF14="",0,AE13*(1+AF14)) -> 3223.2816 | AG13: =IF(AG14="",0,AF13*(1+AG14)) -> 5157.2506 | AH13: =IF(AH14="",0,AG13*(1+AH14)) -> 7735.8758 | AI13: =IF(AI14="",0,AH13*(1+AI14)) -> 10830.226
A14: YOY change | G14: =G13/B13-1 -> 1.2 | H14: =H13/C13-1 -> 1.2 | I14: =I13/D13-1 -> 1.2 | J14: =J13/E13-1 -> 1.2 | K14: =K13/F13-1 -> 1.2 | L14: =L13/G13-1 -> 1.1 | M14: =M13/H13-1 -> 1.1 | N14: =N13/I13-1 -> 1.1 | ... Z14: =Z13/U13-1 -> 0.9 | AA14: 0.8 | AB14: 0.8 | AC14: 0.8 | AD14: 0.8 | AE14: =AE13/Z13-1 -> 0.8 | AF14: 0.7 | AG14: 0.6 | AH14: 0.5 | AI14: 0.4
A15: QOQ change | C15: =C13/B13-1 -> 0.5 | D15: =D13/C13-1 -> 2.3333333 | E15: =E13/D13-1 -> 0.5 | G15: =G13/E13-1 -> -0.70666667 | H15: =H13/G13-1 -> 0.5 | I15: =I13/H13-1 -> 2.3333333 | J15: =J13/I13-1 -> 0.5 | L15: =L13/J13-1 -> -0.72 | M15: =M13/L13-1 -> 0.5 | N15: =N13/M13-1 -> 2.3333333 | O15: =O13/N13-1 -> 0.5 | Q15: =Q13/O13-1 -> -0.73333333 | R15: =R13/Q13-1 -> 0.5 | S15: =S13/R13-1 -> 2.3333333 | T15: =T13/S13-1 -> 0.5 | V15: =V13/T13-1 -> -0.74666667 | W15: =W13/V13-1 -> 0.5 | X15: =X13/W13-1 -> 2.3333333 | Y15: =Y13/X13-1 -> 0.5 | AA15: =AA13/Y13-1 -> -0.76 | AB15: =AB13/AA13-1 -> 0.5 | AC15: =AC13/AB13-1 -> 2.3333333 | AD15: =AD13/AC13-1 -> 0.5
A16: % of total | B16: =B13/B9 -> 0.88888889 | C16: =C13/C9 -> 0.85714286 | D16: =D13/D9 -> 0.93023256 | E16: =E13/E9 -> 0.9375 | F16: =F13/F9 -> 0.92307692 | G16: =G13/G9 -> 0.89795918 | H16: =H13/H9 -> 0.86842105 | I16: =I13/I9 -> 0.93617021 | ... AI16: =AI13/AI9 -> 0.91787605
A18: REVENUE Product #2 | B18: 0.5 | C18: 1 | D18: 1.5 | E18: 2 | F18: =SUM(B18:E18) -> 5 | G18: 1 | H18: 2 | I18: 3 | J18: 4 | K18: =SUM(G18:J18) -> 10 | L18: 1.95 | M18: 3.9 | N18: 5.85 | O18: 7.8 | P18: =SUM(L18:O18) -> 19.5 | Q18: 3.705 | R18: 7.41 | S18: 11.115 | T18: 14.82 | U18: =SUM(Q18:T18) -> 37.05 | V18: 6.85425 | W18: 13.7085 | X18: 20.56275 | Y18: 27.417 | Z18: =SUM(V18:Y18) -> 68.5425 | AA18: =IF(AA19="",0,V18*(1+AA19)) -> 12.33765 | AB18: =IF(AB19="",0,W18*(1+AB19)) -> 24.6753 | AC18: =IF(AC19="",0,X18*(1+AC19)) -> 37.01295 | AD18: =IF(AD19="",0,Y18*(1+AD19)) -> 49.3506 | AE18: =SUM(AA18:AD18) -> 123.3765 | AF18: =IF(AF19="",0,AE18*(1+AF19)) -> 215.90888 | AG18: =IF(AG19="",0,AF18*(1+AG19)) -> 367.04509 | AH18: =IF(AH19="",0,AG18*(1+AH19)) -> 605.62439 | AI18: =IF(AI19="",0,AH18*(1+AI19)) -> 968.99903
A19: YOY change | G19: =G18/B18-1 -> 1 | H19: =H18/C18-1 -> 1 | I19: =I18/D18-1 -> 1 | J19: =J18/E18-1 -> 1 | K19: =K18/F18-1 -> 1 | L19: =L18/G18-1 -> 0.95 | M19: =M18/H18-1 -> 0.95 | N19: =N18/I18-1 -> 0.95 | ... Z19: =Z18/U18-1 -> 0.85 | AA19: 0.8 | AB19: 0.8 | AC19: 0.8 | AD19: 0.8 | AE19: =AE18/Z18-1 -> 0.8 | AF19: 0.75 | AG19: 0.7 | AH19: 0.65 | AI19: 0.6
A20: QOQ change | C20: =C18/B18-1 -> 1 | D20: =D18/C18-1 -> 0.5 | E20: =E18/D18-1 -> 0.33333333 | G20: =G18/E18-1 -> -0.5 | H20: =H18/G18-1 -> 1 | I20: =I18/H18-1 -> 0.5 | J20: =J18/I18-1 -> 0.33333333 | L20: =L18/J18-1 -> -0.5125 | M20: =M18/L18-1 -> 1 | N20: =N18/M18-1 -> 0.5 | O20: =O18/N18-1 -> 0.33333333 | Q20: =Q18/O18-1 -> -0.525 | R20: =R18/Q18-1 -> 1 | S20: =S18/R18-1 -> 0.5 | T20: =T18/S18-1 -> 0.33333333 | V20: =V18/T18-1 -> -0.5375 | W20: =W18/V18-1 -> 1 | X20: =X18/W18-1 -> 0.5 | Y20: =Y18/X18-1 -> 0.33333333 | AA20: =AA18/Y18-1 -> -0.55 | AB20: =AB18/AA18-1 -> 1 | AC20: =AC18/AB18-1 -> 0.5 | AD20: =AD18/AC18-1 -> 0.33333333
A21: % of total | B21: =B18/B9 -> 0.11111111 | C21: =C18/C9 -> 0.14285714 | D21: =D18/D9 -> 0.069767442 | E21: =E18/E9 -> 0.0625 | F21: =F18/F9 -> 0.076923077 | G21: =G18/G9 -> 0.10204082 | H21: =H18/H9 -> 0.13157895 | I21: =I18/I9 -> 0.063829787 | ... AI21: =AI18/AI9 -> 0.082123954

Sheet Income Statement
A1: Income Statement (Revenue from Previous Tab)
A2: $ Values are in $'000s
A3: Blue = hard coded (not calculated)
A4: Green = from previous tab: "Revenue (More Detail)"
G5: =L$5-1 -> -4 | L5: =Q$5-1 -> -3 | Q5: =V$5-1 -> -2 | V5: =AA$5-1 -> -1 | AA5: 0 | AF5: =AA5+1 -> 1 | AG5: =AF5+1 -> 2 | AH5: =AG5+1 -> 3 | AI5: =AH5+1 -> 4 | AJ5: =AI5+1 -> 5
C6: =G7 -> 2021 | G6: FY | H6: =L7 -> 2022 | L6: FY | M6: =Q7 -> 2023 | Q6: FY | R6: =V7 -> 2024 | V6: FY | W6: 2015 | AA6: FY | AB6: =W6+1 -> 2016 | AF6: FYE | AG6: FYE | AH6: FYE | AI6: FYE | AJ6: FYE
C7: ="1Q"&RIGHT(G7,2)&"A" -> 1Q21A | D7: ="2Q"&RIGHT(G7,2)&"A" -> 2Q21A | E7: ="3Q"&RIGHT(G7,2)&"A" -> 3Q21A | F7: ="4Q"&RIGHT(G7,2)&"A" -> 4Q21A | G7: =YEAR(TODAY())+G$5 -> 2021 | H7: ="1Q"&RIGHT(L7,2)&"A" -> 1Q22A | I7: ="2Q"&RIGHT(L7,2)&"A" -> 2Q22A | J7: ="3Q"&RIGHT(L7,2)&"A" -> 3Q22A | K7: ="4Q"&RIGHT(L7,2)&"A" -> 4Q22A | L7: =YEAR(TODAY())+L$5 -> 2022 | M7: ="1Q"&RIGHT(Q7,2)&"A" -> 1Q23A | N7: ="2Q"&RIGHT(Q7,2)&"A" -> 2Q23A | O7: ="3Q"&RIGHT(Q7,2)&"A" -> 3Q23A | P7: ="4Q"&RIGHT(Q7,2)&"A" -> 4Q23A | Q7: =YEAR(TODAY())+Q$5 -> 2023 | R7: 1Q19A | S7: 2Q19A | T7: 3Q19A | U7: 4Q19A | V7: =YEAR(TODAY())+V$5 -> 2024 | W7: =IF(MONTH(TODAY())>3,"1Q"&RIGHT(AA7,2)&"A","1Q"&RIGHT(AA7,2)&"A") -> 1Q25A | X7: =IF(MONTH(TODAY())>6,"2Q"&RIGHT(AA7,2)&"A","2Q"&RIGHT(AA7,2)&"A") -> 2Q25A | Y7: =IF(MONTH(TODAY())>9,"3Q"&RIGHT(AA7,2)&"A","3Q"&RIGHT(AA7,2)&"A") -> 3Q25A | Z7: ="4Q"&RIGHT(AA7,2)&"A" -> 4Q25A | AA7: =YEAR(TODAY())+AA$5 -> 2025 | AB7: ="1Q"&RIGHT(AF7,3) -> 1Q26e | AC7: ="2Q"&RIGHT(AF7,3) -> 2Q26e | AD7: ="3Q"&RIGHT(AF7,3) -> 3Q26e | AE7: ="4Q"&RIGHT(AF7,3) -> 4Q26e | AF7: =YEAR(TODAY())+AF$5&"e" -> 2026e | AG7: =YEAR(TODAY())+AG$5&"e" -> 2027e | AH7: =YEAR(TODAY())+AH$5&"e" -> 2028e | AI7: =YEAR(TODAY())+AI$5&"e" -> 2029e | AJ7: =YEAR(TODAY())+AJ$5&"e" -> 2030e
A8: Revenue | C8: ='Revenue (More Detailed)'!B9 -> 4.5 | D8: ='Revenue (More Detailed)'!C9 -> 7 | E8: ='Revenue (More Detailed)'!D9 -> 21.5 | F8: ='Revenue (More Detailed)'!E9 -> 32 | G8: =SUM(C8:F8) -> 65 | H8: ='Revenue (More Detailed)'!G9 -> 9.8 | I8: ='Revenue (More Detailed)'!H9 -> 15.2 | J8: ='Revenue (More Detailed)'!I9 -> 47 | K8: ='Revenue (More Detailed)'!J9 -> 70 | L8: =SUM(H8:K8) -> 142 | M8: ='Revenue (More Detailed)'!L9 -> 20.43 | N8: ='Revenue (More Detailed)'!M9 -> 31.62 | O8: ='Revenue (More Detailed)'!N9 -> 98.25 | P8: ='Revenue (More Detailed)'!O9 -> 146.4 | Q8: =SUM(M8:P8) -> 296.7 | R8: ='Revenue (More Detailed)'!Q9 -> 40.665 | S8: ='Revenue (More Detailed)'!R9 -> 62.85 | T8: ='Revenue (More Detailed)'!S9 -> 195.915 | U8: ='Revenue (More Detailed)'!T9 -> 292.02 | V8: =SUM(R8:U8) -> 591.45 | W8: ='Revenue (More Detailed)'!V9 -> 77.07825 | X8: ='Revenue (More Detailed)'!W9 -> 119.0445 | Y8: ='Revenue (More Detailed)'!X9 -> 371.68275 | Z8: ='Revenue (More Detailed)'!Y9 -> 554.097 | AA8: =SUM(W8:Z8) -> 1121.9025 | AB8: ='Revenue (More Detailed)'!AA9 -> 138.74085 | AC8: ='Revenue (More Detailed)'!AB9 -> 214.2801 | AD8: ='Revenue (More Detailed)'!AC9 -> 669.02895 | AE8: ='Revenue (More Detailed)'!AD9 -> 997.3746 | AF8: ='Revenue (More Detailed)'!AE9 -> 2019.4245 | AG8: ='Revenue (More Detailed)'!AF9 -> 3439.1905 | AH8: ='Revenue (More Detailed)'!AG9 -> 5524.2956 | AI8: ='Revenue (More Detailed)'!AH9 -> 8341.5002 | AJ8: ='Revenue (More Detailed)'!AI9 -> 11799.225
A9: YOY change | H9: =H8/C8-1 -> 1.1777778 | I9: =I8/D8-1 -> 1.1714286 | J9: =J8/E8-1 -> 1.1860465 | K9: =K8/F8-1 -> 1.1875 | L9: =L8/G8-1 -> 1.1846154 | M9: =M8/H8-1 -> 1.0846939 | N9: =N8/I8-1 -> 1.0802632 | O9: =O8/J8-1 -> 1.0904255 | ... AF9: =AF8/AA8-1 -> 0.8 | AG9: =AG8/AF8-1 -> 0.70305474 | AH9: =AH8/AG8-1 -> 0.6062779 | AI9: =AI8/AH8-1 -> 0.5099663 | AJ9: =AJ8/AI8-1 -> 0.41452075
A10: QOQ change | D10: =D8/C8-1 -> 0.55555556 | E10: =E8/D8-1 -> 2.0714286 | F10: =F8/E8-1 -> 0.48837209 | H10: =H8/F8-1 -> -0.69375 | I10: =I8/H8-1 -> 0.55102041 | J10: =J8/I8-1 -> 2.0921053 | K10: =K8/J8-1 -> 0.4893617 | M10: =M8/K8-1 -> -0.70814286 | N10: =N8/M8-1 -> 0.54772394 | O10: =O8/N8-1 -> 2.1072106 | P10: =P8/O8-1 -> 0.49007634 | R10: =R8/P8-1 -> -0.72223361 | S10: =S8/R8-1 -> 0.54555515 | T10: =T8/S8-1 -> 2.1171838 | U10: =U8/T8-1 -> 0.49054437 | W10: =W8/U8-1 -> -0.73605147 | X10: =X8/W8-1 -> 0.54446293 | Y10: =Y8/X8-1 -> 2.1222169 | Z10: =Z8/Y8-1 -> 0.49077943 | AB10: =AB8/Z8-1 -> -0.74960909 | AC10: =AC8/AB8-1 -> 0.54446293 | AD10: =AD8/AC8-1 -> 2.1222169 | AE10: =AE8/AD8-1 -> 0.49077943
A12: COGS | C12: 1.35 | D12: 2.1 | E12: 6.45 | F12: 9.6 | G12: 19.5 | H12: 2.744 | I12: 4.256 | J12: 13.16 | K12: 19.6 | L12: 39.76 | M12: 5.3118 | N12: 8.2212 | O12: 25.545 | P12: 38.064 | Q12: 77.142 | R12: 9.7596 | S12: 15.084 | T12: 47.0196 | U12: 70.0848 | V12: 141.948 | W12: 16.957215 | X12: 26.18979 | Y12: 81.770205 | Z12: 121.90134 | AA12: =SUM(W12:Z12) -> 246.81855 | AB12: =AB8*AB13 -> 27.74817 | AC12: =AC8*AC13 -> 42.85602 | AD12: =AD8*AD13 -> 133.80579 | AE12: =AE8*AE13 -> 199.47492 | AF12: =SUM(AB12:AE12) -> 403.8849 | AG12: =AG8*AG13 -> 619.05429 | AH12: =AH8*AH13 -> 883.8873 | AI12: =AI8*AI13 -> 1167.81 | AJ12: =AJ8*AJ13 -> 1415.907
A13: % of sales | C13: =C12/C8 -> 0.3 | D13: =D12/D8 -> 0.3 | E13: =E12/E8 -> 0.3 | F13: =F12/F8 -> 0.3 | G13: =G12/G8 -> 0.3 | H13: =H12/H8 -> 0.28 | I13: =I12/I8 -> 0.28 | J13: =J12/J8 -> 0.28 | ... AA13: =AA12/AA8 -> 0.22 | AB13: 0.2 | AC13: 0.2 | AD13: 0.2 | AE13: 0.2 | AF13: =AF12/AF$8 -> 0.2 | AG13: 0.18 | AH13: 0.16 | AI13: 0.14 | AJ13: 0.12
A14: Gross profit | C14: =C8-C12 -> 3.15 | D14: =D8-D12 -> 4.9 | E14: =E8-E12 -> 15.05 | F14: =F8-F12 -> 22.4 | G14: =G8-G12 -> 45.5 | H14: =H8-H12 -> 7.056 | I14: =I8-I12 -> 10.944 | J14: =J8-J12 -> 33.84 | ... AJ14: =AJ8-AJ12 -> 10383.318
A15: Gross margin | C15: =C14/C8 -> 0.7 | D15: =D14/D8 -> 0.7 | E15: =E14/E8 -> 0.7 | F15: =F14/F8 -> 0.7 | G15: =G14/G8 -> 0.7 | H15: =H14/H8 -> 0.72 | I15: =I14/I8 -> 0.72 | J15: =J14/J8 -> 0.72 | ... AJ15: =AJ14/AJ8 -> 0.88
A17: Sales and marketing | C17: 0.765 | D17: 1.19 | E17: 3.655 | F17: 5.44 | G17: =SUM(C17:F17) -> 11.05 | H17: 1.568 | I17: 2.432 | J17: 7.52 | K17: 11.2 | L17: =SUM(H17:K17) -> 22.72 | M17: 3.0645 | N17: 4.743 | O17: 14.7375 | P17: 21.96 | Q17: =SUM(M17:P17) -> 44.505 | R17: 5.6931 | S17: 8.799 | T17: 27.4281 | U17: 40.8828 | V17: =SUM(R17:U17) -> 82.803 | W17: =W8*0.13 -> 10.020173 | X17: =X8*0.13 -> 15.475785 | Y17: =Y8*0.13 -> 48.318758 | Z17: =Z8*0.13 -> 72.03261 | AA17: =SUM(W17:Z17) -> 145.84733 | AB17: =AB18*AB8 -> 16.648902 | AC17: =AC18*AC8 -> 25.713612 | AD17: =AD18*AD8 -> 80.283474 | AE17: =AE18*AE8 -> 119.68495 | AF17: =SUM(AB17:AE17) -> 242.33094 | AG17: =AG18*AG8 -> 378.31095 | AH17: =AH18*AH8 -> 552.42956 | AI17: =AI18*AI8 -> 750.73502 | AJ17: =AJ18*AJ8 -> 943.93802
A18: % of sales | C18: =C17/C8 -> 0.17 | D18: =D17/D8 -> 0.17 | E18: =E17/E8 -> 0.17 | F18: =F17/F8 -> 0.17 | G18: =G17/G$8 -> 0.17 | H18: =H17/H8 -> 0.16 | I18: =I17/I8 -> 0.16 | J18: =J17/J8 -> 0.16 | K18: =K17/K8 -> 0.16 | L18: =L17/L$8 -> 0.16 | M18: =M17/M8 -> 0.15 | N18: =N17/N8 -> 0.15 | O18: =O17/O8 -> 0.15 | P18: =P17/P8 -> 0.15 | Q18: =Q17/Q$8 -> 0.15 | R18: =R17/R8 -> 0.14 | S18: =S17/S8 -> 0.14 | T18: =T17/T8 -> 0.14 | U18: =U17/U8 -> 0.14 | V18: =V17/V$8 -> 0.14 | W18: =W17/W8 -> 0.13 | X18: =X17/X8 -> 0.13 | Y18: =Y17/Y8 -> 0.13 | Z18: =Z17/Z8 -> 0.13 | AA18: =AA17/AA$8 -> 0.13 | AB18: 0.12 | AC18: 0.12 | AD18: 0.12 | AE18: 0.12 | AF18: =AF17/AF$8 -> 0.12 | AG18: 0.11 | AH18: 0.1 | AI18: 0.09 | AJ18: 0.08
A19: Product development | C19: 0.72 | D19: 1.12 | E19: 3.44 | F19: 5.12 | G19: =SUM(C19:F19) -> 10.4 | H19: 1.47 | I19: 2.28 | J19: 7.05 | K19: 10.5 | L19: =SUM(H19:K19) -> 21.3 | M19: 2.8602 | N19: 4.4268 | O19: 13.755 | P19: 20.496 | Q19: =SUM(M19:P19) -> 41.538 | R19: 5.28645 | S19: 8.1705 | T19: 25.46895 | U19: 37.9626 | V19: =SUM(R19:U19) -> 76.8885 | W19: 9.24939 | X19: 14.28534 | Y19: 44.60193 | Z19: 66.49164 | AA19: =SUM(W19:Z19) -> 134.6283 | AB19: =AB8*AB20 -> 15.261494 | AC19: =AC8*AC20 -> 23.570811 | AD19: =AD8*AD20 -> 73.593185 | AE19: =AE8*AE20 -> 109.71121 | AF19: =SUM(AB19:AE19) -> 222.1367 | AG19: =AG8*AG20 -> 343.91905 | AH19: =AH8*AH20 -> 497.18661 | AI19: =AI8*AI20 -> 667.32002 | AJ19: =AJ8*AJ20 -> 825.94576
A20: % of sales | C20: =C19/C8 -> 0.16 | D20: =D19/D8 -> 0.16 | E20: =E19/E8 -> 0.16 | F20: =F19/F8 -> 0.16 | G20: =G19/G$8 -> 0.16 | H20: =H19/H8 -> 0.15 | I20: =I19/I8 -> 0.15 | J20: =J19/J8 -> 0.15 | K20: =K19/K8 -> 0.15 | L20: =L19/L$8 -> 0.15 | M20: =M19/M8 -> 0.14 | N20: =N19/N8 -> 0.14 | O20: =O19/O8 -> 0.14 | P20: =P19/P8 -> 0.14 | Q20: =Q19/Q$8 -> 0.14 | R20: =R19/R8 -> 0.13 | S20: =S19/S8 -> 0.13 | T20: =T19/T8 -> 0.13 | U20: =U19/U8 -> 0.13 | V20: =V19/V$8 -> 0.13 | W20: =W19/W8 -> 0.12 | X20: =X19/X8 -> 0.12 | Y20: =Y19/Y8 -> 0.12 | Z20: =Z19/Z8 -> 0.12 | AA20: =AA19/AA$8 -> 0.12 | AB20: 0.11 | AC20: 0.11 | AD20: 0.11 | AE20: 0.11 | AF20: =AF19/AF$8 -> 0.11 | AG20: 0.1 | AH20: 0.09 | AI20: 0.08 | AJ20: 0.07
A21: General and administrative | C21: 0.675 | D21: 1.05 | E21: 3.225 | F21: 4.8 | G21: =SUM(C21:F21) -> 9.75 | H21: 1.372 | I21: 2.128 | J21: 6.58 | K21: 9.8 | L21: =SUM(H21:K21) -> 19.88 | M21: 2.6559 | N21: 4.1106 | O21: 12.7725 | P21: 19.032 | Q21: =SUM(M21:P21) -> 38.571 | R21: 4.8798 | S21: 7.542 | T21: 23.5098 | U21: 35.0424 | V21: =SUM(R21:U21) -> 70.974 | W21: 8.4786075 | X21: 13.094895 | Y21: 40.885103 | Z21: 60.95067 | AA21: =SUM(W21:Z21) -> 123.40928 | AB21: =AB8*AB22 -> 13.874085 | AC21: =AC8*AC22 -> 21.42801 | AD21: =AD8*AD22 -> 66.902895 | AE21: =AE8*AE22 -> 99.73746 | AF21: =SUM(AB21:AE21) -> 201.94245 | AG21: =AG8*AG22 -> 309.52714 | AH21: =AH8*AH22 -> 441.94365 | AI21: =AI8*AI22 -> 583.90502 | AJ21: =AJ8*AJ22 -> 707.95351
A22: % of sales | C22: =C21/C8 -> 0.15 | D22: =D21/D8 -> 0.15 | E22: =E21/E8 -> 0.15 | F22: =F21/F8 -> 0.15 | G22: =G21/G$8 -> 0.15 | H22: =H21/H8 -> 0.14 | I22: =I21/I8 -> 0.14 | J22: =J21/J8 -> 0.14 | K22: =K21/K8 -> 0.14 | L22: =L21/L$8 -> 0.14 | M22: =M21/M8 -> 0.13 | N22: =N21/N8 -> 0.13 | O22: =O21/O8 -> 0.13 | P22: =P21/P8 -> 0.13 | Q22: =Q21/Q$8 -> 0.13 | R22: =R21/R8 -> 0.12 | S22: =S21/S8 -> 0.12 | T22: =T21/T8 -> 0.12 | U22: =U21/U8 -> 0.12 | V22: =V21/V$8 -> 0.12 | W22: =W21/W8 -> 0.11 | X22: =X21/X8 -> 0.11 | Y22: =Y21/Y8 -> 0.11 | Z22: =Z21/Z8 -> 0.11 | AA22: =AA21/AA$8 -> 0.11 | AB22: 0.1 | AC22: 0.1 | AD22: 0.1 | AE22: 0.1 | AF22: =AF21/AF$8 -> 0.1 | AG22: 0.09 | AH22: 0.08 | AI22: 0.07 | AJ22: 0.06
A23: Depreciation | C23: 0.225 | D23: 0.35 | E23: 1.075 | F23: 1.6 | G23: =SUM(C23:F23) -> 3.25 | H23: 0.49 | I23: 0.76 | J23: 2.35 | K23: 3.5 | L23: =SUM(H23:K23) -> 7.1 | M23: 1.0215 | N23: 1.581 | O23: 4.9125 | P23: 7.32 | Q23: =SUM(M23:P23) -> 14.835 | R23: 2.03325 | S23: 3.1425 | T23: 9.79575 | U23: 14.601 | V23: =SUM(R23:U23) -> 29.5725 | W23: 3.8539125 | X23: 5.952225 | Y23: 18.584138 | Z23: 27.70485 | AA23: =SUM(W23:Z23) -> 56.095125 | AB23: =AB8*AB24 -> 6.9370425 | AC23: =AC8*AC24 -> 10.714005 | AD23: =AD8*AD24 -> 33.451448 | AE23: =AE8*AE24 -> 49.86873 | AF23: =SUM(AB23:AE23) -> 100.97123 | AG23: =AG8*AG24 -> 171.95952 | AH23: =AH8*AH24 -> 276.21478 | AI23: =AI8*AI24 -> 417.07501 | AJ23: =AJ8*AJ24 -> 589.96126
A24: % of sales | C24: =C23/C8 -> 0.05 | D24: =D23/D8 -> 0.05 | E24: =E23/E8 -> 0.05 | F24: =F23/F8 -> 0.05 | G24: =G23/G$8 -> 0.05 | H24: =H23/H8 -> 0.05 | I24: =I23/I8 -> 0.05 | J24: =J23/J8 -> 0.05 | K24: =K23/K8 -> 0.05 | L24: =L23/L$8 -> 0.05 | M24: =M23/M8 -> 0.05 | N24: =N23/N8 -> 0.05 | O24: =O23/O8 -> 0.05 | P24: =P23/P8 -> 0.05 | Q24: =Q23/Q$8 -> 0.05 | R24: =R23/R8 -> 0.05 | S24: =S23/S8 -> 0.05 | T24: =T23/T8 -> 0.05 | U24: =U23/U8 -> 0.05 | V24: =V23/V$8 -> 0.05 | W24: =W23/W8 -> 0.05 | X24: =X23/X8 -> 0.05 | Y24: =Y23/Y8 -> 0.05 | Z24: =Z23/Z8 -> 0.05 | AA24: =AA23/AA$8 -> 0.05 | AB24: 0.05 | AC24: 0.05 | AD24: 0.05 | AE24: 0.05 | AF24: =AF23/AF$8 -> 0.05 | AG24: 0.05 | AH24: 0.05 | AI24: 0.05 | AJ24: 0.05
A26: Total expenses | C26: =C12+C17+C19+C21+C23 -> 3.735 | D26: =D12+D17+D19+D21+D23 -> 5.81 | E26: =E12+E17+E19+E21+E23 -> 17.845 | F26: =F12+F17+F19+F21+F23 -> 26.56 | G26: =G12+G17+G19+G21+G23 -> 53.95 | H26: =H12+H17+H19+H21+H23 -> 7.644 | I26: =I12+I17+I19+I21+I23 -> 11.856 | J26: =J12+J17+J19+J21+J23 -> 36.66 | ... AJ26: =AJ12+AJ17+AJ19+AJ21+AJ23 -> 4483.7056
A27: % of sales | C27: =C26/C$8 -> 0.83 | D27: =D26/D$8 -> 0.83 | E27: =E26/E$8 -> 0.83 | F27: =F26/F$8 -> 0.83 | G27: =G26/G$8 -> 0.83 | H27: =H26/H$8 -> 0.78 | I27: =I26/I$8 -> 0.78 | J27: =J26/J$8 -> 0.78 | ... AJ27: =AJ26/AJ$8 -> 0.38
A28: Yoy Change | AB28: =AB26/W26-1 -> 0.65714286 | AC28: =AC26/X26-1 -> 0.65714286 | AD28: =AD26/Y26-1 -> 0.65714286 | AE28: =AE26/Z26-1 -> 0.65714286 | AF28: =AF26/AA26-1 -> 0.65714286 | AG28: =AG26/AF26-1 -> 0.55623968 | AH28: =AH26/AG26-1 -> 0.45474225 | AI28: =AI26/AH26-1 -> 0.35267814 | AJ28: =AJ26/AI26-1 -> 0.2500416
A29: Income (loss) from operations | C29: =C8-C26 -> 0.765 | D29: =D8-D26 -> 1.19 | E29: =E8-E26 -> 3.655 | F29: =F8-F26 -> 5.44 | G29: =G8-G26 -> 11.05 | H29: =H8-H26 -> 2.156 | I29: =I8-I26 -> 3.344 | J29: =J8-J26 -> 10.34 | ... AJ29: =AJ8-AJ26 -> 7315.5196
A30: % of sales | C30: =C29/C$8 -> 0.17 | D30: =D29/D$8 -> 0.17 | E30: =E29/E$8 -> 0.17 | F30: =F29/F$8 -> 0.17 | G30: =G29/G$8 -> 0.17 | H30: =H29/H$8 -> 0.22 | I30: =I29/I$8 -> 0.22 | J30: =J29/J$8 -> 0.22 | ... AJ30: =AJ29/AJ$8 -> 0.62
A31: EBITDA | C31: =C29+C23 -> 0.99 | D31: =D29+D23 -> 1.54 | E31: =E29+E23 -> 4.73 | F31: =F29+F23 -> 7.04 | G31: =G29+G23 -> 14.3 | H31: =H29+H23 -> 2.646 | I31: =I29+I23 -> 4.104 | J31: =J29+J23 -> 12.69 | ... AJ31: =AJ29+AJ23 -> 7905.4809
A32: % of sales | C32: =C31/C$8 -> 0.22 | D32: =D31/D$8 -> 0.22 | E32: =E31/E$8 -> 0.22 | F32: =F31/F$8 -> 0.22 | G32: =G31/G$8 -> 0.22 | H32: =H31/H$8 -> 0.27 | I32: =I31/I$8 -> 0.27 | J32: =J31/J$8 -> 0.27 | ... AJ32: =AJ31/AJ$8 -> 0.67
A33: Interest expense | C33: 1.284875 | D33: 1.143 | E33: 1.143 | F33: 1.304175 | G33: =SUM(C33:F33) -> 4.87505 | H33: 0.875 | I33: 0.875 | J33: 0.875 | K33: 0.875 | L33: =SUM(H33:K33) -> 3.5 | M33: 0.875 | N33: 0.875 | O33: 0.875 | P33: 0.875 | Q33: =SUM(M33:P33) -> 3.5 | R33: 0.875 | S33: 0.875 | T33: 0.875 | U33: 0.875 | V33: =SUM(R33:U33) -> 3.5 | W33: 0.875 | X33: 0.875 | Y33: 0.875 | Z33: 0.875 | AA33: =SUM(W33:Z33) -> 3.5 | AB33: 0.875 | AC33: 0.875 | AD33: 0.875 | AE33: 0.875 | AF33: =SUM(AB33:AE33) -> 3.5 | AG33: 3.5 | AH33: 3.5 | AI33: 3.5 | AJ33: 3.5
A34: % of sales | C34: =C33/C$8 -> 0.28552778 | D34: =D33/D$8 -> 0.16328571 | E34: =E33/E$8 -> 0.053162791 | F34: =F33/F$8 -> 0.040755469 | G34: =G33/G$8 -> 0.075000769 | H34: =H33/H$8 -> 0.089285714 | I34: =I33/I$8 -> 0.057565789 | J34: =J33/J$8 -> 0.018617021 | ... AJ34: =AJ33/AJ$8 -> 0.00029662965
A35: Profit before tax | C35: =C29-C33 -> -0.519875 | D35: =D29-D33 -> 0.047 | E35: =E29-E33 -> 2.512 | F35: =F29-F33 -> 4.135825 | G35: =G29-G33 -> 6.17495 | H35: =H29-H33 -> 1.281 | I35: =I29-I33 -> 2.469 | J35: =J29-J33 -> 9.465 | ... AJ35: =AJ29-AJ33 -> 7312.0196
A36: % of sales | C36: =C35/C$8 -> -0.11552778 | D36: =D35/D$8 -> 0.0067142857 | E36: =E35/E$8 -> 0.11683721 | F36: =F35/F$8 -> 0.12924453 | G36: =G35/G$8 -> 0.094999231 | H36: =H35/H$8 -> 0.13071429 | I36: =I35/I$8 -> 0.16243421 | J36: =J35/J$8 -> 0.20138298 | ... AJ36: =AJ35/AJ$8 -> 0.61970337
A37: Income tax | C37: 0 | D37: 0 | E37: 0.8 | F37: 1.3 | G37: =SUM(C37:F37) -> 2.1 | H37: 0.4 | I37: 0.8 | J37: 3 | K37: 3.1 | L37: =SUM(H37:K37) -> 7.3 | M37: 1.95483 | N37: 2.86122 | O37: 8.25825 | P37: 12.1584 | Q37: =SUM(M37:P37) -> 25.2327 | R37: 4.20384 | S37: 6.3336 | T37: 19.10784 | U37: 28.33392 | V37: =SUM(R37:U37) -> 57.9792 | W37: 8.3092841 | X37: 12.799673 | Y37: 40.994285 | Z37: 61.38 | AA37: =SUM(W37:Z37) -> 123.48324 | AB37: 17.218847 | AC37: 26.736793 | AD37: 84.035148 | AE37: 125.4067 | AF37: =SUM(AB37:AE37) -> 253.39749 | AG37: 484.66336 | AH37: 861.52762 | AI37: 1426.134 | AJ37: 2194.3934
A39: Net income | C39: =C35-C37 -> -0.519875 | D39: =D35-D37 -> 0.047 | E39: =E35-E37 -> 1.712 | F39: =F35-F37 -> 2.835825 | G39: =G35-G37 -> 4.07495 | H39: =H35-H37 -> 0.881 | I39: =I35-I37 -> 1.669 | J39: =J35-J37 -> 6.465 | ... Z39: =Z35-Z37 -> 142.76089 | AA39: =SUM(W39:Z39) -> 288.12068 | AB39: =AB35-AB37 -> 40.17731 | AC39: =AC35-AC37 -> 62.385849 | AD39: =AD35-AD37 -> 196.08201 | AE39: =AE35-AE37 -> 292.61563 | AF39: =AF35-AF37 -> 591.2608 | AG39: =AG35-AG37 -> 1128.2562 | AH39: =AH35-AH37 -> 2007.6061 | AI39: =AI35-AI37 -> 3325.0211 | AJ39: =AJ35-AJ37 -> 5117.6262
A40: % of sales | C40: =C39/C$8 -> -0.11552778 | D40: =D39/D$8 -> 0.0067142857 | E40: =E39/E$8 -> 0.079627907 | F40: =F39/F$8 -> 0.088619531 | G40: =G39/G$8 -> 0.062691538 | H40: =H39/H$8 -> 0.089897959 | I40: =I39/I$8 -> 0.10980263 | J40: =J39/J$8 -> 0.13755319 | ... AJ40: =AJ39/AJ$8 -> 0.43372562
A41: GAAP Shares | C41: 1165 | D41: 1165 | E41: 1165 | F41: 1165 | G41: 1165 | H41: 1165 | I41: 1165 | J41: 1165 | K41: 1165 | L41: 1165 | M41: 1165 | N41: 1165 | O41: 1165 | P41: 1165 | Q41: =P41 -> 1165 | R41: 1165 | S41: 1165 | T41: 1165 | U41: 1165 | V41: =U41 -> 1165 | W41: 1165 | X41: 1165 | Y41: 1165 | Z41: 1165 | AA41: =Z41 -> 1165 | AB41: 1165 | AC41: 1165 | AD41: 1165 | AE41: 1165 | AF41: =AE41 -> 1165 | AG41: 1165 | AH41: 1165 | AI41: 1165 | AJ41: 1165
A43: Tax Rate | C43: =C37/C35 -> 0 | D43: =D37/D35 -> 0 | E43: =E37/E35 -> 0.31847134 | F43: =F37/F35 -> 0.31432665 | G43: =G37/G35 -> 0.34008373 | H43: =H37/H35 -> 0.31225605 | I43: =I37/I35 -> 0.32401782 | J43: =J37/J35 -> 0.31695721 | ... AJ43: =AJ37/AJ35 -> 0.3001077

Sheet Balance Sheet
A1: Balance Sheet
A2: $ Values are in $'000s
A4: Blue = hard coded (not calculated)
A5: Green = from other tabs | F5: =K$5-1 -> -4 | K5: =P$5-1 -> -3 | P5: =U$5-1 -> -2 | U5: =Z$5-1 -> -1 | Z5: 0 | AE5: =Z5+1 -> 1 | AF5: =AE5+1 -> 2 | AG5: =AF5+1 -> 3 | AH5: =AG5+1 -> 4 | AI5: =AH5+1 -> 5
A6: Balance Sheet (in '000s). | B6: =F7 -> 2021 | F6: FY | G6: =K7 -> 2022 | K6: FY | L6: =P7 -> 2023 | P6: FY | Q6: =U7 -> 2024 | U6: FY | V6: =Z7 -> 2025 | Z6: FY | AA6: =AE7 -> 2026e | AE6: FYE | AF6: FYE | AG6: FYE | AH6: FYE | AI6: FYE
B7: ="1Q"&RIGHT(F7,2)&"A" -> 1Q21A | C7: ="2Q"&RIGHT(F7,2)&"A" -> 2Q21A | D7: ="3Q"&RIGHT(F7,2)&"A" -> 3Q21A | E7: ="4Q"&RIGHT(F7,2)&"A" -> 4Q21A | F7: =YEAR(TODAY())+F$5 -> 2021 | G7: ="1Q"&RIGHT(K7,2)&"A" -> 1Q22A | H7: ="2Q"&RIGHT(K7,2)&"A" -> 2Q22A | I7: ="3Q"&RIGHT(K7,2)&"A" -> 3Q22A | J7: ="4Q"&RIGHT(K7,2)&"A" -> 4Q22A | K7: =YEAR(TODAY())+K$5 -> 2022 | L7: ="1Q"&RIGHT(P7,2)&"A" -> 1Q23A | M7: ="2Q"&RIGHT(P7,2)&"A" -> 2Q23A | N7: ="3Q"&RIGHT(P7,2)&"A" -> 3Q23A | O7: ="4Q"&RIGHT(P7,2)&"A" -> 4Q23A | P7: =YEAR(TODAY())+P$5 -> 2023 | Q7: ="1Q"&RIGHT(U7,2)&"A" -> 1Q24A | R7: ="2Q"&RIGHT(U7,2)&"A" -> 2Q24A | S7: ="3Q"&RIGHT(U7,2)&"A" -> 3Q24A | T7: ="4Q"&RIGHT(U7,2)&"A" -> 4Q24A | U7: =YEAR(TODAY())+U$5 -> 2024 | V7: =IF(MONTH(TODAY())>3,"1Q"&RIGHT(Z7,2)&"A","1Q"&RIGHT(Z7,2)&"A") -> 1Q25A | W7: =IF(MONTH(TODAY())>6,"2Q"&RIGHT(Z7,2)&"A","2Q"&RIGHT(Z7,2)&"A") -> 2Q25A | X7: =IF(MONTH(TODAY())>9,"3Q"&RIGHT(Z7,2)&"A","3Q"&RIGHT(Z7,2)&"A") -> 3Q25A | Y7: ="4Q"&RIGHT(Z7,2)&"A" -> 4Q25A | Z7: =YEAR(TODAY())+Z$5 -> 2025 | AA7: ="1Q"&RIGHT(AE7,3) -> 1Q26e | AB7: ="2Q"&RIGHT(AE7,3) -> 2Q26e | AC7: ="3Q"&RIGHT(AE7,3) -> 3Q26e | AD7: ="4Q"&RIGHT(AE7,3) -> 4Q26e | AE7: =YEAR(TODAY())+AE$5&"e" -> 2026e | AF7: =YEAR(TODAY())+AF$5&"e" -> 2027e | AG7: =YEAR(TODAY())+AG$5&"e" -> 2028e | AH7: =YEAR(TODAY())+AH$5&"e" -> 2029e | AI7: =YEAR(TODAY())+AI$5&"e" -> 2030e
A9: Current assets
A10: Cash and cash equivalents | B10: 96.500062 | C10: 84.847062 | D10: 85.484062 | E10: 99.613887 | F10: 99.613887 | G10: 67.396888 | H10: 67.603888 | I10: 67.584888 | J10: 72.519887 | K10: 72.519887 | L10: 80.628757 | M10: 82.394237 | N10: 86.214087 | O10: 99.129187 | P10: 99.129187 | Q10: 118.77545 | R10: 125.6523 | S10: 141.26806 | T10: 178.41089 | U10: 178.41089 | V10: 221.83407 | W10: 240.79803 | X10: 285.02425 | Y10: 376.36644 | Z10: 376.36644 | AA10: 463.603 | AB10: 505.45474 | AC10: 608.96796 | AD10: 809.02993 | AE10: 809.02993 | AF10: 1447.8905 | AG10: 2908.2182 | AH10: 5449.9277 | AI10: 9528.0884
A11: Short-term investments | B11: 6.5450625 | C11: 6.5450625 | D11: 6.5450625 | E11: 6.5450625 | F11: 6.5450625 | G11: 6.5450625 | H11: 6.5450625 | I11: 6.5450625 | J11: 6.5450625 | K11: 6.5450625 | L11: 6.5450625 | M11: 6.5450625 | N11: 6.5450625 | O11: 6.5450625 | P11: 6.5450625 | Q11: 6.5450625 | R11: 6.5450625 | S11: 6.5450625 | T11: 6.5450625 | U11: 6.5450625 | V11: 6.5450625 | W11: 6.5450625 | X11: 6.5450625 | Y11: 6.5450625 | Z11: 6.5450625 | AA11: 6.5450625 | AB11: 6.5450625 | AC11: 6.5450625 | AD11: 6.5450625 | AE11: 6.5450625 | AF11: 6.5450625 | AG11: 6.5450625 | AH11: 6.5450625 | AI11: 6.5450625
A12: Accounts receivable | B12: 2 | C12: 2 | D12: 2 | E12: 2 | F12: 2 | G12: 0.49 | H12: 0.76 | I12: 2.35 | J12: 3.5 | K12: 3.5 | L12: 1.0215 | M12: 1.581 | N12: 4.9125 | O12: 7.32 | P12: 7.32 | Q12: 2.03325 | R12: 3.1425 | S12: 9.79575 | T12: 14.601 | U12: 14.601 | V12: 3.8539125 | W12: 5.952225 | X12: 18.584138 | Y12: 27.70485 | Z12: 27.70485 | AA12: 6.9370425 | AB12: 10.714005 | AC12: 33.451448 | AD12: 49.86873 | AE12: 49.86873 | AF12: 171.95952 | AG12: 276.21478 | AH12: 417.07501 | AI12: 589.96126
A13: Accounts Receivable as a % of revenue | B13: =B12/'Income Statement'!C8 -> 0.44444444 | C13: =C12/'Income Statement'!D8 -> 0.28571429 | D13: =D12/'Income Statement'!E8 -> 0.093023256 | E13: =E12/'Income Statement'!F8 -> 0.0625 | F13: =E13 -> 0.0625 | G13: =G12/'Income Statement'!H8 -> 0.05 | H13: =H12/'Income Statement'!I8 -> 0.05 | I13: =I12/'Income Statement'!J8 -> 0.05 | J13: =J12/'Income Statement'!K8 -> 0.05 | K13: =J13 -> 0.05 | L13: =L12/'Income Statement'!M8 -> 0.05 | M13: =M12/'Income Statement'!N8 -> 0.05 | N13: =N12/'Income Statement'!O8 -> 0.05 | O13: =O12/'Income Statement'!P8 -> 0.05 | P13: =O13 -> 0.05 | Q13: =Q12/'Income Statement'!R8 -> 0.05 | R13: =R12/'Income Statement'!S8 -> 0.05 | S13: =S12/'Income Statement'!T8 -> 0.05 | T13: =T12/'Income Statement'!U8 -> 0.05 | U13: =T13 -> 0.05 | V13: =V12/'Income Statement'!W8 -> 0.05 | W13: =W12/'Income Statement'!X8 -> 0.05 | X13: =X12/'Income Statement'!Y8 -> 0.05 | Y13: =Y12/'Income Statement'!Z8 -> 0.05 | Z13: =Y13 -> 0.05 | AA13: =AA12/'Income Statement'!AB8 -> 0.05 | AB13: =AB12/'Income Statement'!AC8 -> 0.05 | AC13: =AC12/'Income Statement'!AD8 -> 0.05 | AD13: =AD12/'Income Statement'!AE8 -> 0.05 | AE13: =AD13 -> 0.05 | AF13: =AF12/'Income Statement'!AG8 -> 0.05 | AG13: =AG12/'Income Statement'!AH8 -> 0.05 | AH13: =AH12/'Income Statement'!AI8 -> 0.05 | AI13: =AI12/'Income Statement'!AJ8 -> 0.05
A14: Inventory | B14: 2 | C14: 2 | D14: 2 | E14: 2 | F14: 2 | G14: 1.078 | H14: 1.672 | I14: 5.17 | J14: 7.7 | K14: 7.7 | L14: 2.2473 | M14: 3.4782 | N14: 10.8075 | O14: 16.104 | P14: 16.104 | Q14: 4.47315 | R14: 6.9135 | S14: 21.55065 | T14: 32.1222 | U14: 32.1222 | V14: 8.4786075 | W14: 13.094895 | X14: 40.885103 | Y14: 60.95067 | Z14: 60.95067 | AA14: =AA15*'Income Statement'!AB8 -> 15.261494 | AB14: =AB15*'Income Statement'!AC8 -> 23.570811 | AC14: =AC15*'Income Statement'!AD8 -> 73.593185 | AD14: =AD15*'Income Statement'!AE8 -> 109.71121 | AE14: 109.71121 | AF14: =AF15*'Income Statement'!AG8 -> 378.31095 | AG14: =AG15*'Income Statement'!AH8 -> 607.67252 | AH14: =AH15*'Income Statement'!AI8 -> 917.56503 | AI14: =AI15*'Income Statement'!AJ8 -> 1297.9148
A15: Inventory as a % of revenue | B15: =B14/'Income Statement'!C8 -> 0.44444444 | C15: =C14/'Income Statement'!D8 -> 0.28571429 | D15: =D14/'Income Statement'!E8 -> 0.093023256 | E15: =E14/'Income Statement'!F8 -> 0.0625 | F15: =E15 -> 0.0625 | G15: =G14/'Income Statement'!H8 -> 0.11 | H15: =H14/'Income Statement'!I8 -> 0.11 | I15: =I14/'Income Statement'!J8 -> 0.11 | J15: =J14/'Income Statement'!K8 -> 0.11 | K15: =J15 -> 0.11 | L15: =L14/'Income Statement'!M8 -> 0.11 | M15: =M14/'Income Statement'!N8 -> 0.11 | N15: =N14/'Income Statement'!O8 -> 0.11 | O15: =O14/'Income Statement'!P8 -> 0.11 | P15: =O15 -> 0.11 | Q15: =Q14/'Income Statement'!R8 -> 0.11 | R15: =R14/'Income Statement'!S8 -> 0.11 | S15: =S14/'Income Statement'!T8 -> 0.11 | T15: =T14/'Income Statement'!U8 -> 0.11 | U15: =T15 -> 0.11 | V15: =V14/'Income Statement'!W8 -> 0.11 | W15: =W14/'Income Statement'!X8 -> 0.11 | X15: =X14/'Income Statement'!Y8 -> 0.11 | Y15: =Y14/'Income Statement'!Z8 -> 0.11 | Z15: =Y15 -> 0.11 | AA15: 0.11 | AB15: 0.11 | AC15: 0.11 | AD15: 0.11 | AE15: =AD15 -> 0.11 | AF15: 0.11 | AG15: 0.11 | AH15: 0.11 | AI15: 0.11
A16: Total Current Assets | B16: =B14+B12+B11+B10 -> 107.04512 | C16: =C14+C12+C11+C10 -> 95.392125 | D16: =D14+D12+D11+D10 -> 96.029125 | E16: =E14+E12+E11+E10 -> 110.15895 | F16: =F14+F12+F11+F10 -> 110.15895 | G16: =G14+G12+G11+G10 -> 75.50995 | H16: =H14+H12+H11+H10 -> 76.58095 | I16: =I14+I12+I11+I10 -> 81.64995 | ... AI16: =AI14+AI12+AI11+AI10 -> 11422.509
A17: Long Term Assets
A18: Net fixed assets | B18: =B20-B19 -> 0.225 | C18: =B18-C19+C20 -> 0.575 | D18: =C18-D19+D20 -> 1.65 | E18: =D18-E19+E20 -> 3.25 | F18: =E18 -> 3.25 | G18: =E18-G19+G20 -> 3.74 | H18: =G18-H19+H20 -> 4.5 | I18: =H18-I19+I20 -> 6.85 | J18: =I18-J19+J20 -> 10.35 | K18: =J18 -> 10.35 | L18: =J18-L19+L20 -> 11.3715 | M18: =L18-M19+M20 -> 12.9525 | N18: =M18-N19+N20 -> 17.865 | O18: =N18-O19+O20 -> 25.185 | P18: =O18 -> 25.185 | Q18: =O18-Q19+Q20 -> 27.21825 | R18: =Q18-R19+R20 -> 30.36075 | S18: =R18-S19+S20 -> 40.1565 | T18: =S18-T19+T20 -> 54.7575 | U18: =T18 -> 54.7575 | V18: =T18-V19+V20 -> 58.611413 | W18: =V18-W19+W20 -> 64.563638 | X18: =W18-X19+X20 -> 83.147775 | Y18: =X18-Y19+Y20 -> 110.85263 | Z18: =Y18 -> 110.85263 | AA18: =Y18-AA19+AA20 -> 117.78967 | AB18: =AA18-AB19+AB20 -> 128.50367 | AC18: =AB18-AC19+AC20 -> 161.95512 | AD18: =AC18-AD19+AD20 -> 211.82385 | AE18: =AD18 -> 211.82385 | AF18: =AD18-AF19+AF20 -> 383.78337 | AG18: =AF18-AG19+AG20 -> 659.99816 | AH18: =AG18-AH19+AH20 -> 1077.0732 | AI18: =AH18-AI19+AI20 -> 1667.0344
A19: Depreciation | B19: ='Income Statement'!C23 -> 0.225 | C19: ='Income Statement'!D23 -> 0.35 | D19: ='Income Statement'!E23 -> 1.075 | E19: ='Income Statement'!F23 -> 1.6 | F19: ='Income Statement'!G23 -> 3.25 | G19: ='Income Statement'!H23 -> 0.49 | H19: ='Income Statement'!I23 -> 0.76 | I19: ='Income Statement'!J23 -> 2.35 | ... AI19: ='Income Statement'!AJ23 -> 589.96126
A20: Gross value* | B20: 0.45 | C20: 0.7 | D20: 2.15 | E20: 3.2 | F20: 6.5 | G20: 0.98 | H20: 1.52 | I20: 4.7 | J20: 7 | K20: 14.2 | L20: 2.043 | M20: 3.162 | N20: 9.825 | O20: 14.64 | P20: 29.67 | Q20: 4.0665 | R20: 6.285 | S20: 19.5915 | T20: 29.202 | U20: 59.145 | V20: 7.707825 | W20: 11.90445 | X20: 37.168275 | Y20: 55.4097 | Z20: 112.19025 | AA20: 13.874085 | AB20: 21.42801 | AC20: 66.902895 | AD20: 99.73746 | AE20: 201.94245 | AF20: 343.91905 | AG20: 552.42956 | AH20: 834.15002 | AI20: 1179.9225
A23: Total Long Term Assets | B23: =B18 -> 0.225 | C23: =C18 -> 0.575 | D23: =D18 -> 1.65 | E23: =E18 -> 3.25 | F23: =E23 -> 3.25 | G23: =G18 -> 3.74 | H23: =H18 -> 4.5 | I23: =I18 -> 6.85 | J23: =J18 -> 10.35 | K23: =J23 -> 10.35 | L23: =L18 -> 11.3715 | M23: =M18 -> 12.9525 | N23: =N18 -> 17.865 | O23: =O18 -> 25.185 | P23: =O23 -> 25.185 | Q23: =Q18 -> 27.21825 | R23: =R18 -> 30.36075 | S23: =S18 -> 40.1565 | T23: =T18 -> 54.7575 | U23: =T23 -> 54.7575 | V23: =V18 -> 58.611413 | W23: =W18 -> 64.563638 | X23: =X18 -> 83.147775 | Y23: =Y18 -> 110.85263 | Z23: =Y23 -> 110.85263 | AA23: =AA18 -> 117.78967 | AB23: =AB18 -> 128.50367 | AC23: =AC18 -> 161.95512 | AD23: =AD18 -> 211.82385 | AE23: =AD23 -> 211.82385 | AF23: =AF18 -> 383.78337 | AG23: =AG18 -> 659.99816 | AH23: =AH18 -> 1077.0732 | AI23: =AI18 -> 1667.0344
A24: TOTAL ASSETS | B24: =B23+B16 -> 107.27012 | C24: =C23+C16 -> 95.967125 | D24: =D23+D16 -> 97.679125 | E24: =E23+E16 -> 113.40895 | F24: =E24 -> 113.40895 | G24: =G23+G16 -> 79.24995 | H24: =H23+H16 -> 81.08095 | I24: =I23+I16 -> 88.49995 | J24: =J23+J16 -> 100.61495 | K24: =J24 -> 100.61495 | L24: =L23+L16 -> 101.81412 | M24: =M23+M16 -> 106.951 | N24: =N23+N16 -> 126.34415 | O24: =O23+O16 -> 154.28325 | P24: =O24 -> 154.28325 | Q24: =Q23+Q16 -> 159.04516 | R24: =R23+R16 -> 172.61411 | S24: =S23+S16 -> 219.31602 | T24: =T23+T16 -> 286.43665 | U24: =T24 -> 286.43665 | V24: =V23+V16 -> 299.32307 | W24: =W23+W16 -> 330.95385 | X24: =X23+X16 -> 434.18633 | Y24: =Y23+Y16 -> 582.41964 | Z24: =Y24 -> 582.41964 | AA24: =AA23+AA16 -> 610.13627 | AB24: =AB23+AB16 -> 674.7883 | AC24: =AC23+AC16 -> 884.51277 | AD24: =AD23+AD16 -> 1186.9788 | AE24: =AD24 -> 1186.9788 | AF24: =AF23+AF16 -> 2388.4894 | AG24: =AG23+AG16 -> 4458.6487 | AH24: =AH23+AH16 -> 7868.1859 | AI24: =AI23+AI16 -> 13089.544
A27: Current liabilities
A28: Accounts payable | B28: 1 | C28: 1 | D28: 1 | E28: 1 | F28: 1 | G28: 0.294 | H28: 0.456 | I28: 1.41 | J28: 2.1 | K28: 2.1 | L28: 0.6129 | M28: 0.9486 | N28: 2.9475 | O28: 4.392 | P28: 4.392 | Q28: 1.21995 | R28: 1.8855 | S28: 5.87745 | T28: 8.7606 | U28: 8.7606 | V28: 2.3123475 | W28: 3.571335 | X28: 11.150482 | Y28: 16.62291 | Z28: 16.62291 | AA28: 4.1622255 | AB28: 6.428403 | AC28: 20.070869 | AD28: 29.921238 | AE28: 29.921238 | AF28: 103.17571 | AG28: 165.72887 | AH28: 250.24501 | AI28: 353.97676
A29: Accounts Payable as a % of revenue | B29: =B28/'Income Statement'!C8 -> 0.22222222 | C29: =C28/'Income Statement'!D8 -> 0.14285714 | D29: =D28/'Income Statement'!E8 -> 0.046511628 | E29: =E28/'Income Statement'!F8 -> 0.03125 | F29: =E29 -> 0.03125 | G29: =G28/'Income Statement'!H8 -> 0.03 | H29: =H28/'Income Statement'!I8 -> 0.03 | I29: =I28/'Income Statement'!J8 -> 0.03 | J29: =J28/'Income Statement'!K8 -> 0.03 | K29: =J29 -> 0.03 | L29: =L28/'Income Statement'!M8 -> 0.03 | M29: =M28/'Income Statement'!N8 -> 0.03 | N29: =N28/'Income Statement'!O8 -> 0.03 | O29: =O28/'Income Statement'!P8 -> 0.03 | P29: =O29 -> 0.03 | Q29: =Q28/'Income Statement'!R8 -> 0.03 | R29: =R28/'Income Statement'!S8 -> 0.03 | S29: =S28/'Income Statement'!T8 -> 0.03 | T29: =T28/'Income Statement'!U8 -> 0.03 | U29: =T29 -> 0.03 | V29: =V28/'Income Statement'!W8 -> 0.03 | W29: =W28/'Income Statement'!X8 -> 0.03 | X29: =X28/'Income Statement'!Y8 -> 0.03 | Y29: =Y28/'Income Statement'!Z8 -> 0.03 | Z29: =Y29 -> 0.03 | AA29: =AA28/'Income Statement'!AB8 -> 0.03 | AB29: =AB28/'Income Statement'!AC8 -> 0.03 | AC29: =AC28/'Income Statement'!AD8 -> 0.03 | AD29: =AD28/'Income Statement'!AE8 -> 0.03 | AE29: =AD29 -> 0.03 | AF29: =AF28/'Income Statement'!AG8 -> 0.03 | AG29: =AG28/'Income Statement'!AH8 -> 0.03 | AH29: =AH28/'Income Statement'!AI8 -> 0.03 | AI29: =AI28/'Income Statement'!AJ8 -> 0.03
A30: Short-term debt | B30: 52.79 | C30: 41.44 | D30: 41.44 | E30: 54.334 | F30: =E30 -> 54.334 | G30: 20 | H30: 20 | I30: 20 | J30: 20 | K30: =J30 -> 20 | L30: 20 | M30: 20 | N30: 20 | O30: 20 | P30: =O30 -> 20 | Q30: 20 | R30: 20 | S30: 20 | T30: 20 | U30: =T30 -> 20 | V30: 20 | W30: 20 | X30: 20 | Y30: 20 | Z30: =Y30 -> 20 | AA30: 20 | AB30: 20 | AC30: 20 | AD30: 20 | AE30: =AD30 -> 20 | AF30: 20 | AG30: 20 | AH30: 20 | AI30: 20
A31: Total Current Liabilities | B31: =B28+B30 -> 53.79 | C31: =C28+C30 -> 42.44 | D31: =D28+D30 -> 42.44 | E31: =E28+E30 -> 55.334 | F31: =F28+F30 -> 55.334 | G31: =G28+G30 -> 20.294 | H31: =H28+H30 -> 20.456 | I31: =I28+I30 -> 21.41 | ... AI31: =AI28+AI30 -> 373.97676
A32: Long Term Liabilities
A33: Long-term debt | B33: 50 | C33: 50 | D33: 50 | E33: 50 | F33: =E33 -> 50 | G33: 50 | H33: 50 | I33: 50 | J33: 50 | K33: =J33 -> 50 | L33: 50 | M33: 50 | N33: 50 | O33: 50 | P33: =O33 -> 50 | Q33: 50 | R33: 50 | S33: 50 | T33: 50 | U33: =T33 -> 50 | V33: 50 | W33: 50 | X33: 50 | Y33: 50 | Z33: =Y33 -> 50 | AA33: 50 | AB33: 50 | AC33: 50 | AD33: 50 | AE33: =AD33 -> 50 | AF33: 50 | AG33: 50 | AH33: 50 | AI33: 50
A34: Total Long Term Liabilities | B34: =B33 -> 50 | C34: =C33 -> 50 | D34: =D33 -> 50 | E34: =E33 -> 50 | F34: =E34 -> 50 | G34: =G33 -> 50 | H34: =H33 -> 50 | I34: =I33 -> 50 | J34: =J33 -> 50 | K34: =J34 -> 50 | L34: =L33 -> 50 | M34: =M33 -> 50 | N34: =N33 -> 50 | O34: =O33 -> 50 | P34: =O34 -> 50 | Q34: =Q33 -> 50 | R34: =R33 -> 50 | S34: =S33 -> 50 | T34: =T33 -> 50 | U34: =T34 -> 50 | V34: =V33 -> 50 | W34: =W33 -> 50 | X34: =X33 -> 50 | Y34: =Y33 -> 50 | Z34: =Y34 -> 50 | AA34: =AA33 -> 50 | AB34: =AB33 -> 50 | AC34: =AC33 -> 50 | AD34: =AD33 -> 50 | AE34: =AD34 -> 50 | AF34: =AF33 -> 50 | AG34: =AG33 -> 50 | AH34: =AH33 -> 50 | AI34: =AI33 -> 50
A35: TOTAL LIABILITIES | B35: =B34+B31 -> 103.79 | C35: =C34+C31 -> 92.44 | D35: =D34+D31 -> 92.44 | E35: =E34+E31 -> 105.334 | F35: =E35 -> 105.334 | G35: =G34+G31 -> 70.294 | H35: =H34+H31 -> 70.456 | I35: =I34+I31 -> 71.41 | J35: =J34+J31 -> 72.1 | K35: =J35 -> 72.1 | L35: =L34+L31 -> 70.6129 | M35: =M34+M31 -> 70.9486 | N35: =N34+N31 -> 72.9475 | O35: =O34+O31 -> 74.392 | P35: =O35 -> 74.392 | Q35: =Q34+Q31 -> 71.21995 | R35: =R34+R31 -> 71.8855 | S35: =S34+S31 -> 75.87745 | T35: =T34+T31 -> 78.7606 | U35: =T35 -> 78.7606 | V35: =V34+V31 -> 72.312348 | W35: =W34+W31 -> 73.571335 | X35: =X34+X31 -> 81.150482 | Y35: =Y34+Y31 -> 86.62291 | Z35: =Y35 -> 86.62291 | AA35: =AA34+AA31 -> 74.162226 | AB35: =AB34+AB31 -> 76.428403 | AC35: =AC34+AC31 -> 90.070869 | AD35: =AD34+AD31 -> 99.921238 | AE35: =AD35 -> 99.921238 | AF35: =AF34+AF31 -> 173.17571 | AG35: =AG34+AG31 -> 235.72887 | AH35: =AH34+AH31 -> 320.24501 | AI35: =AI34+AI31 -> 423.97676
A38: Retained Earnings | B38: ='Income Statement'!C39 -> -0.519875 | C38: =B38+'Income Statement'!D39 -> -0.472875 | D38: =C38+'Income Statement'!E39 -> 1.239125 | E38: =D38+'Income Statement'!F39 -> 4.07495 | F38: =E38 -> 4.07495 | G38: =E38+'Income Statement'!H39 -> 4.95595 | H38: =G38+'Income Statement'!I39 -> 6.62495 | I38: =H38+'Income Statement'!J39 -> 13.08995 | J38: =I38+'Income Statement'!K39 -> 24.51495 | K38: =J38 -> 24.51495 | L38: =J38+'Income Statement'!M39 -> 27.20122 | M38: =L38+'Income Statement'!N39 -> 32.0024 | N38: =M38+'Income Statement'!O39 -> 49.39665 | O38: =N38+'Income Statement'!P39 -> 75.89125 | P38: =O38 -> 75.89125 | Q38: =O38+'Income Statement'!R39 -> 83.82521 | R38: =Q38+'Income Statement'!S39 -> 96.72861 | S38: =R38+'Income Statement'!T39 -> 139.43857 | T38: =S38+'Income Statement'!U39 -> 203.67605 | U38: =T38 -> 203.67605 | V38: =T38+'Income Statement'!W39 -> 223.01072 | W38: =V38+'Income Statement'!X39 -> 253.38251 | X38: =W38+'Income Statement'!Y39 -> 349.03584 | Y38: =X38+'Income Statement'!Z39 -> 491.79673 | Z38: =Y38 -> 491.79673 | AA38: =Y38+'Income Statement'!AB39 -> 531.97404 | AB38: =AA38+'Income Statement'!AC39 -> 594.35989 | AC38: =AB38+'Income Statement'!AD39 -> 790.4419 | AD38: =AC38+'Income Statement'!AE39 -> 1083.0575 | AE38: =AD38 -> 1083.0575 | AF38: =AD38+'Income Statement'!AG39 -> 2211.3137 | AG38: =AF38+'Income Statement'!AH39 -> 4218.9198 | AH38: =AG38+'Income Statement'!AI39 -> 7543.9409 | AI38: =AH38+'Income Statement'!AJ39 -> 12661.567
A39: Common Shares | B39: 4 | C39: 4 | D39: 4 | E39: 4 | F39: =E39 -> 4 | G39: 4 | H39: 4 | I39: 4 | J39: 4 | K39: =J39 -> 4 | L39: 4 | M39: 4 | N39: 4 | O39: 4 | P39: =O39 -> 4 | Q39: 4 | R39: 4 | S39: 4 | T39: 4 | U39: =T39 -> 4 | V39: 4 | W39: 4 | X39: 4 | Y39: 4 | Z39: =Y39 -> 4 | AA39: 4 | AB39: 4 | AC39: 4 | AD39: 4 | AE39: =AD39 -> 4 | AF39: 4 | AG39: 4 | AH39: 4 | AI39: 4
A40: TOTAL SHAREHOLDER'S EQUITY | B40: =SUM(B38:B39) -> 3.480125 | C40: =SUM(C38:C39) -> 3.527125 | D40: =SUM(D38:D39) -> 5.239125 | E40: =SUM(E38:E39) -> 8.07495 | F40: =E40 -> 8.07495 | G40: =SUM(G38:G39) -> 8.95595 | H40: =SUM(H38:H39) -> 10.62495 | I40: =SUM(I38:I39) -> 17.08995 | J40: =SUM(J38:J39) -> 28.51495 | K40: =J40 -> 28.51495 | L40: =SUM(L38:L39) -> 31.20122 | M40: =SUM(M38:M39) -> 36.0024 | N40: =SUM(N38:N39) -> 53.39665 | O40: =SUM(O38:O39) -> 79.89125 | P40: =O40 -> 79.89125 | Q40: =SUM(Q38:Q39) -> 87.82521 | R40: =SUM(R38:R39) -> 100.72861 | S40: =SUM(S38:S39) -> 143.43857 | T40: =SUM(T38:T39) -> 207.67605 | U40: =T40 -> 207.67605 | V40: =SUM(V38:V39) -> 227.01072 | W40: =SUM(W38:W39) -> 257.38251 | X40: =SUM(X38:X39) -> 353.03584 | Y40: =SUM(Y38:Y39) -> 495.79673 | Z40: =Y40 -> 495.79673 | AA40: =SUM(AA38:AA39) -> 535.97404 | AB40: =SUM(AB38:AB39) -> 598.35989 | AC40: =SUM(AC38:AC39) -> 794.4419 | AD40: =SUM(AD38:AD39) -> 1087.0575 | AE40: =AD40 -> 1087.0575 | AF40: =SUM(AF38:AF39) -> 2215.3137 | AG40: =SUM(AG38:AG39) -> 4222.9198 | AH40: =SUM(AH38:AH39) -> 7547.9409 | AI40: =SUM(AI38:AI39) -> 12665.567
A42: TOTAL LIABILITIES AND SHAREHOLDERS' EQUITY | B42: =B40+B35 -> 107.27012 | C42: =C40+C35 -> 95.967125 | D42: =D40+D35 -> 97.679125 | E42: =E40+E35 -> 113.40895 | F42: =E42 -> 113.40895 | G42: =G40+G35 -> 79.24995 | H42: =H40+H35 -> 81.08095 | I42: =I40+I35 -> 88.49995 | J42: =J40+J35 -> 100.61495 | K42: =J42 -> 100.61495 | L42: =L40+L35 -> 101.81412 | M42: =M40+M35 -> 106.951 | N42: =N40+N35 -> 126.34415 | O42: =O40+O35 -> 154.28325 | P42: =O42 -> 154.28325 | Q42: =Q40+Q35 -> 159.04516 | R42: =R40+R35 -> 172.61411 | S42: =S40+S35 -> 219.31602 | T42: =T40+T35 -> 286.43665 | U42: =T42 -> 286.43665 | V42: =V40+V35 -> 299.32307 | W42: =W40+W35 -> 330.95385 | X42: =X40+X35 -> 434.18633 | Y42: =Y40+Y35 -> 582.41964 | Z42: =Y42 -> 582.41964 | AA42: =AA40+AA35 -> 610.13627 | AB42: =AB40+AB35 -> 674.7883 | AC42: =AC40+AC35 -> 884.51277 | AD42: =AD40+AD35 -> 1186.9788 | AE42: =AD42 -> 1186.9788 | AF42: =AF40+AF35 -> 2388.4894 | AG42: =AG40+AG35 -> 4458.6487 | AH42: =AH40+AH35 -> 7868.1859 | AI42: =AI40+AI35 -> 13089.544
A43: Do Assets = Liabilities + Equity? | B43: =IF(ROUND(B42,6)=ROUND(B24,6),"YES","NO") -> YES | C43: =IF(ROUND(C42,6)=ROUND(C24,6),"YES","NO") -> YES | D43: =IF(ROUND(D42,6)=ROUND(D24,6),"YES","NO") -> YES | E43: =IF(ROUND(E42,6)=ROUND(E24,6),"YES","NO") -> YES | F43: =IF(ROUND(F42,6)=ROUND(F24,6),"YES","NO") -> YES | G43: =IF(ROUND(G42,6)=ROUND(G24,6),"YES","NO") -> YES | H43: =IF(ROUND(H42,6)=ROUND(H24,6),"YES","NO") -> YES | I43: =IF(ROUND(I42,6)=ROUND(I24,6),"YES","NO") -> YES | ... AI43: =IF(ROUND(AI42,6)=ROUND(AI24,6),"YES","NO") -> YES
B44: =B42-B24 -> 0 | C44: =C42-C24 -> 0 | D44: =D42-D24 -> 0 | E44: =E42-E24 -> 0 | F44: =F42-F24 -> 0 | G44: =G42-G24 -> 0 | H44: =H42-H24 -> 0 | I44: =I42-I24 -> 0 | ... AI44: =AI42-AI24 -> 0
A47: * including FA disposal | B47: 0.0225 | C47: 0.035 | D47: 0.1075 | E47: 0.16 | F47: 0.325 | G47: 0.049 | H47: 0.076 | I47: 0.235 | J47: 0.35 | K47: 0.71 | L47: 0.10215 | M47: 0.1581 | N47: 0.49125 | O47: 0.732 | P47: 1.4835 | Q47: 0.203325 | R47: 0.31425 | S47: 0.979575 | T47: 1.4601 | U47: 2.95725 | V47: 0.38539125 | W47: 0.5952225 | X47: 1.8584138 | Y47: 2.770485 | Z47: 5.6095125 | AE47: 30 | AF47: 62 | AG47: 31 | AH47: 180 | AI47: 376
A49: D/E | B49: =(B30+B33)/B40 -> 29.536295 | C49: =(C30+C33)/C40 -> 25.924797 | D49: =(D30+D33)/D40 -> 17.453296 | E49: =(E30+E33)/E40 -> 12.920699 | F49: =(F30+F33)/F40 -> 12.920699 | G49: =(G30+G33)/G40 -> 7.8160329 | H49: =(H30+H33)/H40 -> 6.5882663 | I49: =(I30+I33)/I40 -> 4.0959745 | ... AI49: =(AI30+AI33)/AI40 -> 0.0055267955
